textract_cli/__init__.py
textract_cli/__main__.py
textract_cli/cli.py
textract_cli-0.1.dist-info/LICENSE
textract_cli-0.1.dist-info/METADATA
textract_cli-0.1.dist-info/WHEEL
textract_cli-0.1.dist-info/entry_points.txt
textract_cli-0.1.dist-info/top_level.txt
textract_cli-0.1.dist-info/RECORD
