Metadata-Version: 2.1
Name: textract-cli
Version: 0.1
Summary: CLI for running files through AWS Textract
Author: Simon Willison
License: Apache-2.0
Project-URL: Homepage, https://github.com/simonw/textract-cli
Project-URL: Changelog, https://github.com/simonw/textract-cli/releases
Project-URL: Issues, https://github.com/simonw/textract-cli/issues
Project-URL: CI, https://github.com/simonw/textract-cli/actions
Classifier: License :: OSI Approved :: Apache Software License
Requires-Python: >=3.8
License-File: LICENSE
Requires-Dist: click
Requires-Dist: boto3
Provides-Extra: test
Requires-Dist: pytest ; extra == 'test'
Requires-Dist: moto[textract] ; extra == 'test'
